{"_class":"page","do_objectID":"KgFRIh66YQRM2CTN4O1Aa","booleanOperation":-1,"isFixedToViewport":false,"isFlippedHorizontal":false,"isFlippedVertical":false,"isLocked":false,"isTemplate":false,"isVisible":true,"hasCustomPrototypeVisibility":false,"hasExplicitConstraints":true,"horizontalSizing":3,"horizontalPins":0,"verticalSizing":3,"verticalPins":0,"prototypeVisibility":1,"prototypeVisibilityTrigger":2,"layerListExpandedType":0,"name":"页面 1","nameIsFixed":false,"resizingConstraint":63,"resizingType":0,"rotation":0,"shouldBreakMaskChain":false,"exportOptions":{"_class":"exportOptions","includedLayerIds":[],"layerOptions":0,"shouldTrim":false,"exportFormats":[]},"frame":{"_class":"rect","constrainProportions":false,"height":0,"width":0,"x":0,"y":0},"clippingMaskMode":0,"hasClippingMask":false,"prototypeScrolling":0,"style":{"_class":"style","do_objectID":"4ZtWNR_Uwqg2RpGhUj-3A","endMarkerType":0,"miterLimit":10,"startMarkerType":0,"windingRule":1,"skipCorners":true,"blurs":[],"borderOptions":{"_class":"borderOptions","isEnabled":true,"dashPattern":[],"lineCapStyle":0,"lineJoinStyle":0},"borders":[],"colorControls":{"_class":"colorControls","isEnabled":false,"brightness":0,"contrast":1,"hue":0,"saturation":1},"contextSettings":{"_class":"graphicsContextSettings","blendMode":0,"opacity":1},"fills":[],"shadows":[]},"groupBehavior":0,"overlayBackgroundInteraction":0,"presentationStyle":0,"clippingBehavior":0,"includeBackgroundColorInExport":true,"isFlowHome":false,"leftPadding":0,"topPadding":0,"rightPadding":0,"bottomPadding":0,"paddingSelection":1,"prototypeScrollingArea":0,"groupLayout":{"_class":"MSImmutableFreeformGroupLayout"},"layers":[{"_class":"group","do_objectID":"0:5","booleanOperation":-1,"isFixedToViewport":false,"isFlippedHorizontal":false,"isFlippedVertical":false,"isLocked":false,"isTemplate":false,"isVisible":true,"hasCustomPrototypeVisibility":false,"hasExplicitConstraints":true,"horizontalSizing":3,"horizontalPins":0,"verticalSizing":3,"verticalPins":0,"prototypeVisibility":1,"prototypeVisibilityTrigger":2,"layerListExpandedType":2,"name":"分组 1","nameIsFixed":false,"resizingConstraint":63,"resizingType":0,"rotation":0,"shouldBreakMaskChain":false,"exportOptions":{"_class":"exportOptions","includedLayerIds":[],"layerOptions":0,"shouldTrim":false,"exportFormats":[]},"frame":{"_class":"rect","constrainProportions":false,"height":720,"width":1280,"x":-50,"y":161},"clippingMaskMode":0,"hasClippingMask":false,"prototypeScrolling":0,"style":{"_class":"style","do_objectID":"5nzKNGON9fePi9mifUeqD","endMarkerType":0,"miterLimit":10,"startMarkerType":0,"windingRule":1,"skipCorners":true,"blurs":[],"borderOptions":{"_class":"borderOptions","isEnabled":true,"dashPattern":[0,0],"lineCapStyle":0,"lineJoinStyle":0},"borders":[],"colorControls":{"_class":"colorControls","isEnabled":false,"brightness":0,"contrast":1,"hue":0,"saturation":1},"contextSettings":{"_class":"graphicsContextSettings","blendMode":0,"opacity":1},"fills":[],"shadows":[]},"groupBehavior":0,"overlayBackgroundInteraction":0,"presentationStyle":0,"clippingBehavior":0,"includeBackgroundColorInExport":true,"isFlowHome":false,"leftPadding":0,"topPadding":0,"rightPadding":0,"bottomPadding":0,"paddingSelection":1,"prototypeScrollingArea":0,"groupLayout":{"_class":"MSImmutableFreeformGroupLayout"},"layers":[{"_class":"shapePath","do_objectID":"yU0OOFg2WxT20mr9BX67M","booleanOperation":-1,"isFixedToViewport":false,"isFlippedHorizontal":false,"isFlippedVertical":false,"isLocked":false,"isTemplate":false,"isVisible":true,"hasCustomPrototypeVisibility":false,"hasExplicitConstraints":true,"horizontalSizing":3,"horizontalPins":0,"verticalSizing":3,"verticalPins":0,"prototypeVisibility":1,"prototypeVisibilityTrigger":2,"layerListExpandedType":1,"name":"图层 16.png","nameIsFixed":false,"resizingConstraint":63,"resizingType":0,"rotation":0,"shouldBreakMaskChain":false,"exportOptions":{"_class":"exportOptions","includedLayerIds":[],"layerOptions":0,"shouldTrim":false,"exportFormats":[]},"frame":{"_class":"rect","constrainProportions":false,"height":720,"width":1280,"x":0,"y":0},"clippingMaskMode":0,"hasClippingMask":false,"prototypeScrolling":0,"style":{"_class":"style","do_objectID":"HWKogsTfgLSKw1Ogry7pO","endMarkerType":0,"miterLimit":10,"startMarkerType":0,"windingRule":1,"skipCorners":true,"blurs":[],"borderOptions":{"_class":"borderOptions","isEnabled":true,"dashPattern":[0,0],"lineCapStyle":0,"lineJoinStyle":0},"borders":[],"colorControls":{"_class":"colorControls","isEnabled":false,"brightness":0,"contrast":1,"hue":0,"saturation":1},"contextSettings":{"_class":"graphicsContextSettings","blendMode":0,"opacity":1},"fills":[{"_class":"fill","isEnabled":true,"fillType":4,"color":{"_class":"color","alpha":1,"blue":0.8,"green":0.8,"red":0.8},"contextSettings":{"_class":"graphicsContextSettings","blendMode":0,"opacity":1},"gradient":{"_class":"gradient","elipseLength":0,"from":"{0.5, 0}","gradientType":0,"to":"{0.5, 1}","stops":[{"_class":"gradientStop","position":0,"color":{"_class":"color","alpha":1,"blue":1,"green":1,"red":1}},{"_class":"gradientStop","position":1,"color":{"_class":"color","alpha":1,"blue":0,"green":0,"red":0}}]},"image":{"_class":"MSJSONFileReference","_ref_class":"MSImageData","_ref":"images\/512c0171e1606143e31eee052d865afc3e63d63b.png"},"noiseIndex":0,"noiseIntensity":0,"patternFillType":1,"patternTileScale":1,"layeringType":0}],"shadows":[]},"edited":false,"isClosed":true,"pointRadiusBehaviour":1,"points":[{"_class":"curvePoint","cornerRadius":0,"cornerStyle":0,"curveFrom":"{0, 0}","curveMode":1,"curveTo":"{0, 0}","hasCurveFrom":false,"hasCurveTo":false,"point":"{0, 0}"},{"_class":"curvePoint","cornerRadius":0,"cornerStyle":0,"curveFrom":"{0, 0}","curveMode":1,"curveTo":"{0, 0}","hasCurveFrom":false,"hasCurveTo":false,"point":"{1, 0}"},{"_class":"curvePoint","cornerRadius":0,"cornerStyle":0,"curveFrom":"{0, 0}","curveMode":1,"curveTo":"{0, 0}","hasCurveFrom":false,"hasCurveTo":false,"point":"{1, 1}"},{"_class":"curvePoint","cornerRadius":0,"cornerStyle":0,"curveFrom":"{0, 0}","curveMode":1,"curveTo":"{0, 0}","hasCurveFrom":false,"hasCurveTo":false,"point":"{0, 1}"}]},{"_class":"text","do_objectID":"3DA70616-568D-4550-B19D-C93B4B880869","booleanOperation":-1,"isFixedToViewport":false,"isFlippedHorizontal":false,"isFlippedVertical":false,"isLocked":false,"isTemplate":false,"isVisible":true,"hasCustomPrototypeVisibility":false,"hasExplicitConstraints":false,"horizontalSizing":3,"horizontalPins":0,"verticalSizing":3,"verticalPins":0,"prototypeVisibility":1,"prototypeVisibilityTrigger":2,"layerListExpandedType":1,"name":"输入文本","nameIsFixed":false,"resizingConstraint":63,"resizingType":0,"rotation":0,"shouldBreakMaskChain":false,"exportOptions":{"_class":"exportOptions","includedLayerIds":[],"layerOptions":0,"shouldTrim":false,"exportFormats":[]},"frame":{"_class":"rect","constrainProportions":false,"height":119,"width":321,"x":116,"y":139},"clippingMaskMode":0,"hasClippingMask":false,"prototypeScrolling":0,"style":{"_class":"style","do_objectID":"EC04920E-E019-468F-9984-8E41653B459C","endMarkerType":0,"miterLimit":10,"startMarkerType":0,"windingRule":1,"skipCorners":true,"blurs":[],"borderOptions":{"_class":"borderOptions","isEnabled":true,"dashPattern":[],"lineCapStyle":0,"lineJoinStyle":0},"borders":[],"colorControls":{"_class":"colorControls","isEnabled":false,"brightness":0,"contrast":1,"hue":0,"saturation":1},"contextSettings":{"_class":"graphicsContextSettings","blendMode":0,"opacity":1},"fills":[],"shadows":[],"textStyle":{"_class":"textStyle","encodedAttributes":{"MSAttributedStringColorAttribute":{"_class":"color","alpha":1,"blue":0,"green":0,"red":0},"MSAttributedStringFontAttribute":{"_class":"fontDescriptor","attributes":{"name":"PingFangSC-Regular","size":12}}},"verticalAlignment":0,"skipColors":false,"skipAlignment":false}},"attributedString":{"_class":"attributedString","string":"输入文本","attributes":[{"_class":"stringAttribute","location":0,"length":4,"attributes":{"MSAttributedStringColorAttribute":{"_class":"color","alpha":1,"blue":0,"green":0,"red":0},"MSAttributedStringFontAttribute":{"_class":"fontDescriptor","attributes":{"name":"PingFangSC-Regular","size":12}}}}]},"automaticallyDrawOnUnderlyingPath":false,"dontSynchroniseWithSymbol":false,"glyphBounds":"{{0, 3}, {48, 12}}","lineSpacingBehaviour":3},{"_class":"shapePath","do_objectID":"b-_qo03HAGfm5BiOF4I8P","booleanOperation":-1,"isFixedToViewport":false,"isFlippedHorizontal":false,"isFlippedVertical":false,"isLocked":false,"isTemplate":false,"isVisible":true,"hasCustomPrototypeVisibility":false,"hasExplicitConstraints":true,"horizontalSizing":3,"horizontalPins":0,"verticalSizing":3,"verticalPins":0,"prototypeVisibility":1,"prototypeVisibilityTrigger":2,"layerListExpandedType":1,"name":"图层 14.png","nameIsFixed":false,"resizingConstraint":63,"resizingType":0,"rotation":0,"shouldBreakMaskChain":false,"exportOptions":{"_class":"exportOptions","includedLayerIds":[],"layerOptions":0,"shouldTrim":false,"exportFormats":[]},"frame":{"_class":"rect","constrainProportions":false,"height":88,"width":420,"x":97,"y":495},"clippingMaskMode":0,"hasClippingMask":false,"prototypeScrolling":0,"style":{"_class":"style","do_objectID":"z_yx-e0toiEtxD486CWlt","endMarkerType":0,"miterLimit":10,"startMarkerType":0,"windingRule":1,"skipCorners":true,"blurs":[],"borderOptions":{"_class":"borderOptions","isEnabled":true,"dashPattern":[0,0],"lineCapStyle":0,"lineJoinStyle":0},"borders":[],"colorControls":{"_class":"colorControls","isEnabled":false,"brightness":0,"contrast":1,"hue":0,"saturation":1},"contextSettings":{"_class":"graphicsContextSettings","blendMode":0,"opacity":1},"fills":[{"_class":"fill","isEnabled":true,"fillType":4,"color":{"_class":"color","alpha":1,"blue":0.8,"green":0.8,"red":0.8},"contextSettings":{"_class":"graphicsContextSettings","blendMode":0,"opacity":1},"gradient":{"_class":"gradient","elipseLength":0,"from":"{0.5, 0}","gradientType":0,"to":"{0.5, 1}","stops":[{"_class":"gradientStop","position":0,"color":{"_class":"color","alpha":1,"blue":1,"green":1,"red":1}},{"_class":"gradientStop","position":1,"color":{"_class":"color","alpha":1,"blue":0,"green":0,"red":0}}]},"image":{"_class":"MSJSONFileReference","_ref_class":"MSImageData","_ref":"images\/f393fdffa20587785e9dd84d411f1af34fc21214.png"},"noiseIndex":0,"noiseIntensity":0,"patternFillType":1,"patternTileScale":1,"layeringType":0}],"shadows":[]},"edited":false,"isClosed":true,"pointRadiusBehaviour":1,"points":[{"_class":"curvePoint","cornerRadius":0,"cornerStyle":0,"curveFrom":"{0, 0}","curveMode":1,"curveTo":"{0, 0}","hasCurveFrom":false,"hasCurveTo":false,"point":"{0, 0}"},{"_class":"curvePoint","cornerRadius":0,"cornerStyle":0,"curveFrom":"{0, 0}","curveMode":1,"curveTo":"{0, 0}","hasCurveFrom":false,"hasCurveTo":false,"point":"{1, 0}"},{"_class":"curvePoint","cornerRadius":0,"cornerStyle":0,"curveFrom":"{0, 0}","curveMode":1,"curveTo":"{0, 0}","hasCurveFrom":false,"hasCurveTo":false,"point":"{1, 1}"},{"_class":"curvePoint","cornerRadius":0,"cornerStyle":0,"curveFrom":"{0, 0}","curveMode":1,"curveTo":"{0, 0}","hasCurveFrom":false,"hasCurveTo":false,"point":"{0, 1}"}]},{"_class":"shapePath","do_objectID":"d1H979aJyNQ-xqi6XToOp","booleanOperation":-1,"isFixedToViewport":false,"isFlippedHorizontal":false,"isFlippedVertical":false,"isLocked":false,"isTemplate":false,"isVisible":true,"hasCustomPrototypeVisibility":false,"hasExplicitConstraints":true,"horizontalSizing":3,"horizontalPins":0,"verticalSizing":3,"verticalPins":0,"prototypeVisibility":1,"prototypeVisibilityTrigger":2,"layerListExpandedType":1,"name":"图层 9.png","nameIsFixed":false,"resizingConstraint":63,"resizingType":0,"rotation":0,"shouldBreakMaskChain":false,"exportOptions":{"_class":"exportOptions","includedLayerIds":[],"layerOptions":0,"shouldTrim":false,"exportFormats":[]},"frame":{"_class":"rect","constrainProportions":false,"height":541,"width":558,"x":658,"y":90},"clippingMaskMode":0,"hasClippingMask":false,"prototypeScrolling":0,"style":{"_class":"style","do_objectID":"7Jpofk5hxwZBXD_C7q71m","endMarkerType":0,"miterLimit":10,"startMarkerType":0,"windingRule":1,"skipCorners":true,"blurs":[],"borderOptions":{"_class":"borderOptions","isEnabled":true,"dashPattern":[0,0],"lineCapStyle":0,"lineJoinStyle":0},"borders":[],"colorControls":{"_class":"colorControls","isEnabled":false,"brightness":0,"contrast":1,"hue":0,"saturation":1},"contextSettings":{"_class":"graphicsContextSettings","blendMode":0,"opacity":1},"fills":[{"_class":"fill","isEnabled":true,"fillType":4,"color":{"_class":"color","alpha":1,"blue":0.8,"green":0.8,"red":0.8},"contextSettings":{"_class":"graphicsContextSettings","blendMode":0,"opacity":1},"gradient":{"_class":"gradient","elipseLength":0,"from":"{0.5, 0}","gradientType":0,"to":"{0.5, 1}","stops":[{"_class":"gradientStop","position":0,"color":{"_class":"color","alpha":1,"blue":1,"green":1,"red":1}},{"_class":"gradientStop","position":1,"color":{"_class":"color","alpha":1,"blue":0,"green":0,"red":0}}]},"image":{"_class":"MSJSONFileReference","_ref_class":"MSImageData","_ref":"images\/3c64fce80398d389d709bba79bde07857512f5d3.png"},"noiseIndex":0,"noiseIntensity":0,"patternFillType":1,"patternTileScale":1,"layeringType":0}],"shadows":[]},"edited":false,"isClosed":true,"pointRadiusBehaviour":1,"points":[{"_class":"curvePoint","cornerRadius":0,"cornerStyle":0,"curveFrom":"{0, 0}","curveMode":1,"curveTo":"{0, 0}","hasCurveFrom":false,"hasCurveTo":false,"point":"{0, 0}"},{"_class":"curvePoint","cornerRadius":0,"cornerStyle":0,"curveFrom":"{0, 0}","curveMode":1,"curveTo":"{0, 0}","hasCurveFrom":false,"hasCurveTo":false,"point":"{1, 0}"},{"_class":"curvePoint","cornerRadius":0,"cornerStyle":0,"curveFrom":"{0, 0}","curveMode":1,"curveTo":"{0, 0}","hasCurveFrom":false,"hasCurveTo":false,"point":"{1, 1}"},{"_class":"curvePoint","cornerRadius":0,"cornerStyle":0,"curveFrom":"{0, 0}","curveMode":1,"curveTo":"{0, 0}","hasCurveFrom":false,"hasCurveTo":false,"point":"{0, 1}"}]}]}],"horizontalRulerData":{"_class":"rulerData","base":0,"guides":[]},"verticalRulerData":{"_class":"rulerData","base":0,"guides":[]}}